tracker_utils_tl/__init__.py
tracker_utils_tl/tracker.py
tracker_utils_tl-0.1.6.dist-info/METADATA
tracker_utils_tl-0.1.6.dist-info/WHEEL
tracker_utils_tl-0.1.6.dist-info/top_level.txt
tracker_utils_tl-0.1.6.dist-info/RECORD
