Metadata-Version: 2.4
Name: tracker_utils_tl
Version: 0.1.6
Requires-Python: >=3.8
Requires-Dist: boto3
Dynamic: requires-dist
Dynamic: requires-python
